liteshare/LSClient.cp39-win_amd64.pyd
liteshare/LSClient.py
liteshare/ParquetManager.cp39-win_amd64.pyd
liteshare/ParquetManager.py
liteshare/__init__.py
liteshare-0.1.3.dist-info/METADATA
liteshare-0.1.3.dist-info/WHEEL
liteshare-0.1.3.dist-info/top_level.txt
liteshare-0.1.3.dist-info/RECORD
