Metadata-Version: 2.1
Name: liteshare
Version: 0.1.3
Summary: Data API for Quantitative Analysts.
Home-page: UNKNOWN
Author: Danene Tech Inc.
Author-email: neneli@bignene123.com
License: CC BY-NC
Keywords: Data API for Quants
Platform: UNKNOWN
Requires-Dist: requests
Requires-Dist: pandas
Requires-Dist: redis
Requires-Dist: tqdm
